{"IRSTD": {"2410.07437": "|**2024-10-09**|**Robust infrared small target detection using self-supervised and a contrario paradigms**|Alina Ciocarlan et.al.|[2410.07437](http://arxiv.org/abs/2410.07437)|null|\n", "2409.19599": "|**2024-09-29**|**Gradient is All You Need: Gradient-Based Attention Fusion for Infrared Small Target Detection**|Chen Hu et.al.|[2409.19599](http://arxiv.org/abs/2409.19599)|null|\n", "2409.12448": "|**2024-10-04**|**Infrared Small Target Detection in Satellite Videos: A New Dataset and A Novel Recurrent Feature Refinement Framework**|Xinyi Ying et.al.|[2409.12448](http://arxiv.org/abs/2409.12448)|**[link](https://github.com/xinyiying/rfr)**|\n", "2409.04714": "|**2024-09-07**|**Unleashing the Power of Generic Segmentation Models: A Simple Baseline for Infrared Small Target Detection**|Mingjin Zhang et.al.|[2409.04714](http://arxiv.org/abs/2409.04714)|null|\n", "2409.04011": "|**2024-09-06**|**Hybrid Mask Generation for Infrared Small Target Detection with Single-Point Supervision**|Weijie He et.al.|[2409.04011](http://arxiv.org/abs/2409.04011)|null|\n", "2408.09615": "|**2024-08-18**|**The First Competition on Resource-Limited Infrared Small Target Detection Challenge: Methods and Results**|Boyang Li et.al.|[2408.09615](http://arxiv.org/abs/2408.09615)|**[link](https://github.com/xinyiying/basicirstd)**|\n", "2408.08191": "|**2024-11-16**|**Beyond Full Labels: Energy-Double-Guided Single-Point Prompt for Infrared Small Target Label Generation**|Shuai Yuan et.al.|[2408.08191](http://arxiv.org/abs/2408.08191)|**[link](https://github.com/xdfai/edgsp)**|\n", "2408.04823": "|**2024-09-15**|**One Shot is Enough for Sequential Infrared Small Target Segmentation**|Bingbing Dan et.al.|[2408.04823](http://arxiv.org/abs/2408.04823)|**[link](https://github.com/d-iceice/one-shot-irsts)**|\n", "2408.03717": "|**2024-10-03**|**Pick of the Bunch: Detecting Infrared Small Targets Beyond Hit-Miss Trade-Offs via Selective Rank-Aware Attention**|Yimian Dai et.al.|[2408.03717](http://arxiv.org/abs/2408.03717)|**[link](https://github.com/grokcv/serankdet)**|\n", "2408.02780": "|**2024-08-05**|**LR-Net: A Lightweight and Robust Network for Infrared Small Target Detection**|Chuang Yu et.al.|[2408.02780](http://arxiv.org/abs/2408.02780)|null|\n", "2408.02773": "|**2024-08-05**|**Refined Infrared Small Target Detection Scheme with Single-Point Supervision**|Jinmiao Zhao et.al.|[2408.02773](http://arxiv.org/abs/2408.02773)|null|\n", "2408.01976": "|**2024-08-08**|**Single-Point Supervised High-Resolution Dynamic Network for Infrared Small Target Detection**|Jing Wu et.al.|[2408.01976](http://arxiv.org/abs/2408.01976)|null|\n", "2407.20090": "|**2024-07-29**|**Infrared Small Target Detection based on Adjustable Sensitivity Strategy and Multi-Scale Fusion**|Jinmiao Zhao et.al.|[2407.20090](http://arxiv.org/abs/2407.20090)|null|\n", "2407.20078": "|**2024-11-02**|**Background Semantics Matter: Cross-Task Feature Exchange Network for Clustered Infrared Small Target Detection With Sky-Annotated Dataset**|Mengxuan Xiao et.al.|[2407.20078](http://arxiv.org/abs/2407.20078)|**[link](https://github.com/grokcv/bafe-net)**|\n", "2407.15369": "|**2024-07-22**|**Sparse Prior Is Not All You Need: When Differential Directionality Meets Saliency Coherence for Infrared Small Target Detection**|Fei Zhou et.al.|[2407.15369](http://arxiv.org/abs/2407.15369)|**[link](https://github.com/grokcv/sdd)**|\n", "2407.07520": "|**2024-07-10**|**IRSAM: Advancing Segment Anything Model for Infrared Small Target Detection**|Mingjin Zhang et.al.|[2407.07520](http://arxiv.org/abs/2407.07520)|**[link](https://github.com/ipic-lab/irsam)**|\n", "2406.13445": "|**2024-06-19**|**Lost in UNet: Improving Infrared Small Target Detection by Underappreciated Local Features**|Wuzhou Quan et.al.|[2406.13445](http://arxiv.org/abs/2406.13445)|**[link](https://github.com/wuzhou-quan/hintu)**|\n", "2406.06949": "|**2024-09-05**|**Triple-domain Feature Learning with Frequency-aware Memory Enhancement for Moving Infrared Small Target Detection**|Weiwei Duan et.al.|[2406.06949](http://arxiv.org/abs/2406.06949)|**[link](https://github.com/uestc-nnlab/tridos)**|\n", "2406.02037": "|**2024-11-25**|**Multi-Scale Direction-Aware Network for Infrared Small Target Detection**|Jinmiao Zhao et.al.|[2406.02037](http://arxiv.org/abs/2406.02037)|null|\n", "2406.00632": "|**2024-06-02**|**Diff-Mosaic: Augmenting Realistic Representations in Infrared Small Target Detection via Diffusion Prior**|Yukai Shi et.al.|[2406.00632](http://arxiv.org/abs/2406.00632)|**[link](https://github.com/yupeilin2388/diff-mosaic)**|\n", "2403.19366": "|**2024-03-28**|**Infrared Small Target Detection with Scale and Location Sensitivity**|Qiankun Liu et.al.|[2403.19366](http://arxiv.org/abs/2403.19366)|**[link](https://github.com/ying-fu/mshnet)**|\n", "2403.08380": "|**2024-03-13**|**Mitigate Target-level Insensitivity of Infrared Small Target Detection via Posterior Distribution Modeling**|Haoqing Li et.al.|[2403.08380](http://arxiv.org/abs/2403.08380)|**[link](https://github.com/li-haoqing/irstd-diff)**|\n", "2403.05416": "|**2024-03-08**|**SIRST-5K: Exploring Massive Negatives Synthesis with Self-supervised Learning for Robust Infrared Small Target Detection**|Yahao Lu et.al.|[2403.05416](http://arxiv.org/abs/2403.05416)|**[link](https://github.com/luy0222/sirst-5k)**|\n", "2403.02148": "|**2024-06-24**|**MiM-ISTD: Mamba-in-Mamba for Efficient Infrared Small Target Detection**|Tianxiang Chen et.al.|[2403.02148](http://arxiv.org/abs/2403.02148)|**[link](https://github.com/txchen-ustc/mim-istd)**|\n", "2402.18003": "|**2024-02-28**|**Infrared Small Target Detection via tensor $L_{2,1}$ norm minimization and ASSTV regularization: A Novel Tensor Recovery Approach**|Jiqian Zhao et.al.|[2402.18003](http://arxiv.org/abs/2402.18003)|null|\n", "2402.05410": "|**2024-02-08**|**SpirDet: Towards Efficient, Accurate and Lightweight Infrared Small Target Detector**|Qianchen Mao et.al.|[2402.05410](http://arxiv.org/abs/2402.05410)|null|\n", "2402.02288": "|**2024-02-03**|**$\\textit{A Contrario}$ Paradigm for YOLO-based Infrared Small Target Detection**|Alina Ciocarlan et.al.|[2402.02288](http://arxiv.org/abs/2402.02288)|null|\n", "2402.02046": "|**2024-02-03**|**TCI-Former: Thermal Conduction-Inspired Transformer for Infrared Small Target Detection**|Tianxiang Chen et.al.|[2402.02046](http://arxiv.org/abs/2402.02046)|null|\n", "2401.15583": "|**2024-04-30**|**SCTransNet: Spatial-channel Cross Transformer Network for Infrared Small Target Detection**|Shuai Yuan et.al.|[2401.15583](http://arxiv.org/abs/2401.15583)|**[link](https://github.com/xdfai/sctransnet)**|\n", "2401.15578": "|**2024-06-04**|**ASCNet: Asymmetric Sampling Correction Network for Infrared Image Destriping**|Shuai Yuan et.al.|[2401.15578](http://arxiv.org/abs/2401.15578)|**[link](https://github.com/xdfai/ascnet)**|\n", "2311.08747": "|**2024-01-17**|**Improved Dense Nested Attention Network Based on Transformer for Infrared Small Target Detection**|Chun Bao et.al.|[2311.08747](http://arxiv.org/abs/2311.08747)|**[link](https://github.com/edwardbao1006/bit_sirst)**|\n", "2311.00917": "|**2023-11-02**|**RPCANet: Deep Unfolding RPCA Based Infrared Small Target Detection**|Fengyi Wu et.al.|[2311.00917](http://arxiv.org/abs/2311.00917)|**[link](https://github.com/fengyiwu98/rpcanet)**|\n", "2310.12562": "|**2023-10-19**|**Click on Mask: A Labor-efficient Annotation Framework with Level Set for Infrared Small Target Detection**|Haoqing Li et.al.|[2310.12562](http://arxiv.org/abs/2310.12562)|**[link](https://github.com/li-haoqing/com)**|\n", "2310.05347": "|**2023-10-09**|**Infrared Small Target Detection Using Double-Weighted Multi-Granularity Patch Tensor Model With Tensor-Train Decomposition**|Guiyu Zhang et.al.|[2310.05347](http://arxiv.org/abs/2310.05347)|null|\n", "2309.13646": "|**2023-09-24**|**ILNet: Low-level Matters for Salient Infrared Small Target Detection**|Haoqing Li et.al.|[2309.13646](http://arxiv.org/abs/2309.13646)|**[link](https://github.com/li-haoqing/ilnet)**|\n", "2309.01099": "|**2023-09-03**|**Enhancing Infrared Small Target Detection Robustness with Bi-Level Adversarial Framework**|Zhu Liu et.al.|[2309.01099](http://arxiv.org/abs/2309.01099)|null|\n", "2307.14723": "|**2024-02-27**|**EFLNet: Enhancing Feature Learning for Infrared Small Target Detection**|Bo Yang et.al.|[2307.14723](http://arxiv.org/abs/2307.14723)|**[link](https://github.com/yangbo0411/infrared-small-target)**|\n", "2304.04442": "|**2023-04-10**|**Monte Carlo Linear Clustering with Single-Point Supervision is Enough for Infrared Small Target Detection**|Boyang Li et.al.|[2304.04442](http://arxiv.org/abs/2304.04442)|**[link](https://github.com/yeren123455/sirst-single-point-supervision)**|\n", "2304.01484": "|**2024-10-04**|**Mapping Degeneration Meets Label Evolution: Learning Infrared Small Target Detection with Single Point Supervision**|Xinyi Ying et.al.|[2304.01484](http://arxiv.org/abs/2304.01484)|**[link](https://github.com/xinyiying/lesps)**|\n", "2303.10321": "|**2023-03-18**|**ABC: Attention with Bilinear Correlation for Infrared Small Target Detection**|Peiwen Pan et.al.|[2303.10321](http://arxiv.org/abs/2303.10321)|**[link](https://github.com/panpeiwen/abc)**|\n", "2411.13260": "|**2024-11-20**|**Paying more attention to local contrast: improving infrared small target detection performance via prior knowledge**|Peichao Wang et.al.|[2411.13260](http://arxiv.org/abs/2411.13260)|null|\n"}, "Mamba": {"2411.12603": "|**2024-11-22**|**STREAM: A Universal State-Space Model for Sparse Geometric Data**|Mark Sch\u00f6ne et.al.|[2411.12603](http://arxiv.org/abs/2411.12603)|null|\n", "2411.12537": "|**2024-12-06**|**Unlocking State-Tracking in Linear RNNs Through Negative Eigenvalues**|Riccardo Grazzi et.al.|[2411.12537](http://arxiv.org/abs/2411.12537)|**[link](https://github.com/automl/unlocking_state_tracking)**|\n", "2411.12222": "|**2024-11-19**|**Contrast Similarity-Aware Dual-Pathway Mamba for Multivariate Time Series Node Classification**|Mingsen Du et.al.|[2411.12222](http://arxiv.org/abs/2411.12222)|null|\n", "2411.11843": "|**2024-11-18**|**Bi-Mamba: Towards Accurate 1-Bit State Space Models**|Shengkun Tang et.al.|[2411.11843](http://arxiv.org/abs/2411.11843)|null|\n", "2411.11717": "|**2024-11-18**|**RAWMamba: Unified sRGB-to-RAW De-rendering With State Space Model**|Hongjun Chen et.al.|[2411.11717](http://arxiv.org/abs/2411.11717)|null|\n", "2411.11926": "|**2024-11-18**|**KAN-Mamba FusionNet: Redefining Medical Image Segmentation with Non-Linear Modeling**|Akansh Agrawal et.al.|[2411.11926](http://arxiv.org/abs/2411.11926)|null|\n", "2411.11906": "|**2024-11-16**|**$\\text{S}^{3}$Mamba: Arbitrary-Scale Super-Resolution via Scaleable State Space Model**|Peizhe Xia et.al.|[2411.11906](http://arxiv.org/abs/2411.11906)|null|\n", "2411.10543": "|**2024-11-15**|**SoftLMs: Efficient Adaptive Low-Rank Approximation of Language Models using Soft-Thresholding Mechanism**|Priyansh Bhatnagar et.al.|[2411.10543](http://arxiv.org/abs/2411.10543)|null|\n", "2411.10433": "|**2024-11-15**|**M-VAR: Decoupled Scale-wise Autoregressive Modeling for High-Quality Image Generation**|Sucheng Ren et.al.|[2411.10433](http://arxiv.org/abs/2411.10433)|**[link](https://github.com/oliverrensu/mvar)**|\n", "2411.10027": "|**2024-11-15**|**XLSR-Mamba: A Dual-Column Bidirectional State Space Model for Spoofing Attack Detection**|Yang Xiao et.al.|[2411.10027](http://arxiv.org/abs/2411.10027)|null|\n", "2411.09363": "|**2024-11-25**|**When Mamba Meets xLSTM: An Efficient and Precise Method with the XLSTM-VMUNet Model for Skin lesion Segmentation**|Zhuoyi Fang et.al.|[2411.09363](http://arxiv.org/abs/2411.09363)|**[link](https://github.com/fangzhuoyi/xlstm-vmunet)**|\n", "2411.08840": "|**2024-11-13**|**Multimodal Instruction Tuning with Hybrid State Space Models**|Jianing Zhou et.al.|[2411.08840](http://arxiv.org/abs/2411.08840)|null|\n", "2411.08395": "|**2024-11-13**|**MambaXCTrack: Mamba-based Tracker with SSM Cross-correlation and Motion Prompt for Ultrasound Needle Tracking**|Yuelin Zhang et.al.|[2411.08395](http://arxiv.org/abs/2411.08395)|null|\n", "2411.07930": "|**2024-11-29**|**CT-Mamba: A Hybrid Convolutional State Space Model for Low-Dose CT Denoising**|Linxuan Li et.al.|[2411.07930](http://arxiv.org/abs/2411.07930)|**[link](https://github.com/zy2219105/ct-mamba)**|\n", "2411.07873": "|**2024-11-12**|**Diverse capability and scaling of diffusion and auto-regressive models when learning abstract rules**|Binxu Wang et.al.|[2411.07873](http://arxiv.org/abs/2411.07873)|null|\n", "2411.07863": "|**2024-11-12**|**CDXFormer: Boosting Remote Sensing Change Detection with Extended Long Short-Term Memory**|Zhenkai Wu et.al.|[2411.07863](http://arxiv.org/abs/2411.07863)|**[link](https://github.com/xwmaxwma/rschange)**|\n", "2411.07751": "|**2024-11-12**|**SAV-SE: Scene-aware Audio-Visual Speech Enhancement with Selective State Space Model**|Xinyuan Qian et.al.|[2411.07751](http://arxiv.org/abs/2411.07751)|null|\n", "2411.07500": "|**2024-11-12**|**MaDiNet: Mamba Diffusion Network for SAR Target Detection**|Jie Zhou et.al.|[2411.07500](http://arxiv.org/abs/2411.07500)|**[link](https://github.com/joyezlearning/madinet)**|\n", "2411.07364": "|**2024-11-11**|**AEROMamba: An efficient architecture for audio super-resolution using generative adversarial networks and state space models**|Wallace Abreu et.al.|[2411.07364](http://arxiv.org/abs/2411.07364)|null|\n", "2411.06968": "|**2024-11-11**|**Mamba-based Decoder-Only Approach with Bidirectional Speech Modeling for Speech Recognition**|Yoshiki Masuyama et.al.|[2411.06968](http://arxiv.org/abs/2411.06968)|**[link](https://github.com/YoshikiMas/madeon-asr)**|\n", "2411.06798": "|**2024-11-11**|**LA4SR: illuminating the dark proteome with generative AI**|David R. Nelson et.al.|[2411.06798](http://arxiv.org/abs/2411.06798)|null|\n", "2411.06652": "|**2024-11-11**|**LFSamba: Marry SAM with Mamba for Light Field Salient Object Detection**|Zhengyi Liu et.al.|[2411.06652](http://arxiv.org/abs/2411.06652)|null|\n", "2411.06481": "|**2024-11-10**|**KMM: Key Frame Mask Mamba for Extended Motion Generation**|Zeyu Zhang et.al.|[2411.06481](http://arxiv.org/abs/2411.06481)|null|\n", "2411.06318": "|**2024-11-10**|**SEM-Net: Efficient Pixel Modelling for image inpainting with Spatially Enhanced SSM**|Shuang Chen et.al.|[2411.06318](http://arxiv.org/abs/2411.06318)|**[link](https://github.com/chrischen1023/sem-net)**|\n", "2411.06217": "|**2024-11-09**|**Selective State Space Model for Monaural Speech Enhancement**|Moran Chen et.al.|[2411.06217](http://arxiv.org/abs/2411.06217)|null|\n", "2411.04168": "|**2024-11-06**|**DiMSUM: Diffusion Mamba -- A Scalable and Unified Spatial-Frequency Method for Image Generation**|Hao Phung et.al.|[2411.04168](http://arxiv.org/abs/2411.04168)|null|\n", "2411.03945": "|**2024-11-06**|**Can Custom Models Learn In-Context? An Exploration of Hybrid Architecture Performance on In-Context Learning Tasks**|Ryan Campbell et.al.|[2411.03945](http://arxiv.org/abs/2411.03945)|**[link](https://github.com/in-context-learning-2024/in-context)**|\n", "2411.03855": "|**2024-11-06**|**MambaPEFT: Exploring Parameter-Efficient Fine-Tuning for Mamba**|Masakazu Yoshimura et.al.|[2411.03855](http://arxiv.org/abs/2411.03855)|null|\n", "2411.03672": "|**2024-11-06**|**Towards 3D Semantic Scene Completion for Autonomous Driving: A Meta-Learning Framework Empowered by Deformable Large-Kernel Attention and Mamba Model**|Yansong Qu et.al.|[2411.03672](http://arxiv.org/abs/2411.03672)|null|\n", "2411.03260": "|**2024-11-05**|**ShadowMamba: State-Space Model with Boundary-Region Selective Scan for Shadow Removal**|Xiujin Zhu et.al.|[2411.03260](http://arxiv.org/abs/2411.03260)|null|\n", "2411.02941": "|**2024-11-05**|**A Mamba Foundation Model for Time Series Forecasting**|Haoyu Ma et.al.|[2411.02941](http://arxiv.org/abs/2411.02941)|null|\n", "2411.01897": "|**2024-11-12**|**LE-PDE++: Mamba for accelerating PDEs Simulations**|Aoming Liang et.al.|[2411.01897](http://arxiv.org/abs/2411.01897)|null|\n", "2411.01647": "|**2024-11-03**|**Optical Flow Representation Alignment Mamba Diffusion Model for Medical Video Generation**|Zhenbin Wang et.al.|[2411.01647](http://arxiv.org/abs/2411.01647)|null|\n", "2411.01589": "|**2024-11-21**|**BiT-MamSleep: Bidirectional Temporal Mamba for EEG Sleep Staging**|Xinliang Zhou et.al.|[2411.01589](http://arxiv.org/abs/2411.01589)|null|\n", "2411.01399": "|**2024-11-03**|**MambaReg: Mamba-Based Disentangled Convolutional Sparse Coding for Unsupervised Deformable Multi-Modal Image Registration**|Kaiang Wen et.al.|[2411.01399](http://arxiv.org/abs/2411.01399)|null|\n", "2411.01278": "|**2024-11-05**|**A versatile framework for attitude tuning of beamlines at advanced light sources**|Peng-Cheng Li et.al.|[2411.01278](http://arxiv.org/abs/2411.01278)|null|\n", "2411.01258": "|**2024-11-05**|**Beyond the EPICS: comprehensive Python IOC development with QueueIOC**|Peng-Cheng Li et.al.|[2411.01258](http://arxiv.org/abs/2411.01258)|null|\n", "2411.00233": "|**2024-10-31**|**SambaMixer: State of Health Prediction of Li-ion Batteries using Mamba State Space Models**|Jos\u00e9 Ignacio Olalde-Verano et.al.|[2411.00233](http://arxiv.org/abs/2411.00233)|**[link](https://github.com/sascha-kirch/samba-mixer)**|\n", "2411.00151": "|**2024-10-31**|**NIMBA: Towards Robust and Principled Processing of Point Clouds With SSMs**|Nursena K\u00f6pr\u00fcc\u00fc et.al.|[2411.00151](http://arxiv.org/abs/2411.00151)|null|\n", "2410.24070": "|**2024-11-01**|**Dynamical similarity analysis uniquely captures how computations develop in RNNs**|Quentin Guilhot et.al.|[2410.24070](http://arxiv.org/abs/2410.24070)|**[link](https://github.com/qglht/repal)**|\n", "2411.14100": "|**2024-11-21**|**BEST-STD: Bidirectional Mamba-Enhanced Speech Tokenization for Spoken Term Detection**|Anup Singh et.al.|[2411.14100](http://arxiv.org/abs/2411.14100)|null|\n", "2411.16481": "|**2024-11-25**|**Deformable Mamba for Wide Field of View Segmentation**|Jie Hu et.al.|[2411.16481](http://arxiv.org/abs/2411.16481)|**[link](https://github.com/jiehu1996/deformablemamba)**|\n", "2411.16019": "|**2024-11-25**|**M3: Mamba-assisted Multi-Circuit Optimization via MBRL with Effective Scheduling**|Youngmin Oh et.al.|[2411.16019](http://arxiv.org/abs/2411.16019)|null|\n", "2411.15941": "|**2024-11-24**|**MobileMamba: Lightweight Multi-Receptive Visual Mamba Network**|Haoyang He et.al.|[2411.15941](http://arxiv.org/abs/2411.15941)|**[link](https://github.com/lewandofskee/MobileMamba)**|\n", "2411.15761": "|**2024-11-24**|**MambaTrack: Exploiting Dual-Enhancement for Night UAV Tracking**|Chunhui Zhang et.al.|[2411.15761](http://arxiv.org/abs/2411.15761)|null|\n", "2411.15469": "|**2024-11-23**|**Mamba-CL: Optimizing Selective State Space Model in Null Space for Continual Learning**|De Cheng et.al.|[2411.15469](http://arxiv.org/abs/2411.15469)|null|\n", "2411.15459": "|**2024-11-23**|**MambaVLT: Time-Evolving Multimodal State Space Model for Vision-Language Tracking**|Xinqi Liu et.al.|[2411.15459](http://arxiv.org/abs/2411.15459)|null|\n", "2411.15455": "|**2024-11-23**|**MUFM: A Mamba-Enhanced Feedback Model for Micro Video Popularity Prediction**|Jiacheng Lu et.al.|[2411.15455](http://arxiv.org/abs/2411.15455)|null|\n", "2411.15269": "|**2024-11-22**|**MambaIRv2: Attentive State Space Restoration**|Hang Guo et.al.|[2411.15269](http://arxiv.org/abs/2411.15269)|**[link](https://github.com/csguoh/mambair)**|\n", "2411.15255": "|**2024-11-22**|**OSMamba: Omnidirectional Spectral Mamba with Dual-Domain Prior Generator for Exposure Correction**|Gehui Li et.al.|[2411.15255](http://arxiv.org/abs/2411.15255)|null|\n", "2411.15241": "|**2024-11-22**|**EfficientViM: Efficient Vision Mamba with Hidden State Mixer based State Space Duality**|Sanghyeok Lee et.al.|[2411.15241](http://arxiv.org/abs/2411.15241)|**[link](https://github.com/mlvlab/EfficientViM)**|\n", "2411.15224": "|**2024-11-21**|**Parameter Efficient Mamba Tuning via Projector-targeted Diagonal-centric Linear Transformation**|Seokil Ham et.al.|[2411.15224](http://arxiv.org/abs/2411.15224)|null|\n", "2411.17473": "|**2024-11-26**|**TinyViM: Frequency Decoupling for Tiny Hybrid Vision Mamba**|Xiaowen Ma et.al.|[2411.17473](http://arxiv.org/abs/2411.17473)|**[link](https://github.com/xwmaxwma/tinyvim)**|\n", "2411.17207": "|**2024-11-26**|**On the Efficiency of NLP-Inspired Methods for Tabular Deep Learning**|Anton Frederik Thielmann et.al.|[2411.17207](http://arxiv.org/abs/2411.17207)|**[link](https://github.com/basf/mamba-tabular)**|\n", "2411.17980": "|**2024-11-27**|**Vision Mamba Distillation for Low-resolution Fine-grained Image Classification**|Yao Chen et.al.|[2411.17980](http://arxiv.org/abs/2411.17980)|**[link](https://github.com/boa2004plaust/vimd)**|\n", "2411.17770": "|**2024-11-26**|**MTS-UNMixers: Multivariate Time Series Forecasting via Channel-Time Dual Unmixing**|Xuanbing Zhu et.al.|[2411.17770](http://arxiv.org/abs/2411.17770)|**[link](https://github.com/zhu-0108/mts-unmixers)**|\n", "2411.19639": "|**2024-11-29**|**RMIO: A Model-Based MARL Framework for Scenarios with Observation Loss in Some Agents**|Shi Zifeng et.al.|[2411.19639](http://arxiv.org/abs/2411.19639)|null|\n", "2411.18902": "|**2024-11-28**|**MSEMG: Surface Electromyography Denoising with a Mamba-based Efficient Network**|Yu-Tung Liu et.al.|[2411.18902](http://arxiv.org/abs/2411.18902)|null|\n", "2412.02568": "|**2024-12-03**|**Segmentation of Coronary Artery Stenosis in X-ray Angiography using Mamba Models**|Ali Rostami et.al.|[2412.02568](http://arxiv.org/abs/2412.02568)|null|\n", "2412.01422": "|**2024-12-02**|**MamKPD: A Simple Mamba Baseline for Real-Time 2D Keypoint Detection**|Yonghao Dang et.al.|[2412.01422](http://arxiv.org/abs/2412.01422)|null|\n", "2412.01405": "|**2024-12-02**|**MambaU-Lite: A Lightweight Model based on Mamba and Integrated Channel-Spatial Attention for Skin Lesion Segmentation**|Thi-Nhu-Quynh Nguyen et.al.|[2412.01405](http://arxiv.org/abs/2412.01405)|**[link](https://github.com/nqnguyen812/mambau-lite)**|\n", "2412.00833": "|**2024-12-01**|**AlignMamba: Enhancing Multimodal Mamba with Local and Global Cross-modal Alignment**|Yan Li et.al.|[2412.00833](http://arxiv.org/abs/2412.00833)|null|\n", "2412.00776": "|**2024-12-01**|**Learning Mamba as a Continual Learner**|Chongyang Zhao et.al.|[2412.00776](http://arxiv.org/abs/2412.00776)|null|\n", "2412.00725": "|**2024-12-01**|**Decision Transformer vs. Decision Mamba: Analysing the Complexity of Sequential Decision Making in Atari Games**|Ke Yan et.al.|[2412.00725](http://arxiv.org/abs/2412.00725)|**[link](https://github.com/0x1DA9430/Decision-Transformer-vs-Decision-Mamba)**|\n", "2412.00678": "|**2024-12-01**|**2DMamba: Efficient State Space Model for Image Representation with Applications on Giga-Pixel Whole Slide Image Classification**|Jingwei Zhang et.al.|[2412.00678](http://arxiv.org/abs/2412.00678)|**[link](https://github.com/atlasanalyticslab/2dmamba)**|\n", "2412.00626": "|**2024-12-01**|**MambaNUT: Nighttime UAV Tracking via Mamba and Adaptive Curriculum Learning**|You Wu et.al.|[2412.00626](http://arxiv.org/abs/2412.00626)|null|\n", "2412.04861": "|**2024-12-06**|**MSECG: Incorporating Mamba for Robust and Efficient ECG Super-Resolution**|Jie Lin et.al.|[2412.04861](http://arxiv.org/abs/2412.04861)|null|\n", "2412.06211": "|**2024-12-09**|**MSCrackMamba: Leveraging Vision Mamba for Crack Detection in Fused Multispectral Imagery**|Qinfeng Zhu et.al.|[2412.06211](http://arxiv.org/abs/2412.06211)|null|\n", "2412.06148": "|**2024-12-09**|**The Computational Limits of State-Space Models and Mamba via the Lens of Circuit Complexity**|Yifang Chen et.al.|[2412.06148](http://arxiv.org/abs/2412.06148)|null|\n", "2412.07481": "|**2024-12-10**|**Manta: Enhancing Mamba for Few-Shot Action Recognition of Long Sub-Sequence**|Wenbo Huang et.al.|[2412.07481](http://arxiv.org/abs/2412.07481)|null|\n", "2412.07299": "|**2024-12-10**|**Bidirectional Mamba state-space model for anomalous diffusion**|Maxime Lavaud et.al.|[2412.07299](http://arxiv.org/abs/2412.07299)|null|\n", "2412.07222": "|**2024-12-10**|**MPSI: Mamba enhancement model for pixel-wise sequential interaction Image Super-Resolution**|Yuchun He et.al.|[2412.07222](http://arxiv.org/abs/2412.07222)|null|\n", "2412.08482": "|**2024-12-11**|**SAM-Mamba: Mamba Guided SAM Architecture for Generalized Zero-Shot Polyp Segmentation**|Tapas Kumar Dutta et.al.|[2412.08482](http://arxiv.org/abs/2412.08482)|null|\n", "2412.08388": "|**2024-12-11**|**LOMA: Language-assisted Semantic Occupancy Network via Triplane Mamba**|Yubo Cui et.al.|[2412.08388](http://arxiv.org/abs/2412.08388)|null|\n", "2412.08160": "|**2024-12-11**|**DG-Mamba: Robust and Efficient Dynamic Graph Structure Learning with Selective State Space Models**|Haonan Yuan et.al.|[2412.08160](http://arxiv.org/abs/2412.08160)|**[link](https://github.com/RingBDStack/DG-Mamba)**|\n", "2412.09289": "|**2024-12-12**|**Optimising TinyML with Quantization and Distillation of Transformer and Mamba Models for Indoor Localisation on Edge Devices**|Thanaphon Suwannaphong et.al.|[2412.09289](http://arxiv.org/abs/2412.09289)|null|\n", "2412.08947": "|**2024-12-12**|**Selective Visual Prompting in Vision Mamba**|Yifeng Yao et.al.|[2412.08947](http://arxiv.org/abs/2412.08947)|null|\n"}}